blueprints/__init__.py
blueprints/admin.py
blueprints/app_settings.py
blueprints/apps.py
blueprints/auth_hooks.py
blueprints/constants.py
blueprints/decorators.py
blueprints/managers.py
blueprints/models.py
blueprints/providers.py
blueprints/tasks.py
blueprints/urls.py
blueprints/validators.py
blueprints/locale/de/LC_MESSAGES/django.mo
blueprints/locale/de/LC_MESSAGES/django.po
blueprints/locale/en/LC_MESSAGES/django.mo
blueprints/locale/en/LC_MESSAGES/django.po
blueprints/locale/es/LC_MESSAGES/django.mo
blueprints/locale/es/LC_MESSAGES/django.po
blueprints/locale/fr/LC_MESSAGES/django.mo
blueprints/locale/fr/LC_MESSAGES/django.po
blueprints/locale/ja/LC_MESSAGES/django.mo
blueprints/locale/ja/LC_MESSAGES/django.po
blueprints/locale/ko/LC_MESSAGES/django.mo
blueprints/locale/ko/LC_MESSAGES/django.po
blueprints/locale/ru/LC_MESSAGES/django.mo
blueprints/locale/ru/LC_MESSAGES/django.po
blueprints/locale/zh_Hans/LC_MESSAGES/django.mo
blueprints/locale/zh_Hans/LC_MESSAGES/django.po
blueprints/management/commands/blueprints_load_types.py
blueprints/management/commands/blueprints_update_all.py
blueprints/migrations/0001_initial.py
blueprints/migrations/0002_add_locations_permission.py
blueprints/migrations/0003_query_optimizations.py
blueprints/migrations/0004_show_location_details.py
blueprints/migrations/__init__.py
blueprints/static/blueprints/css/blueprints.css
blueprints/static/blueprints/images/Spinner-1s-64px-dark.gif
blueprints/static/blueprints/images/Spinner-1s-64px-light.gif
blueprints/static/blueprints/js/blueprint_list.js
blueprints/static/blueprints/js/manage_blueprint_list.js
blueprints/static/blueprints/js/open_request_list.js
blueprints/static/blueprints/js/user_request_list.js
blueprints/templates/blueprints/base.html
blueprints/templates/blueprints/index.html
blueprints/templates/blueprints/bundles/settings.html
blueprints/templates/blueprints/modals/modal_dialog.html
blueprints/templates/blueprints/modals/view_blueprint_content.html
aa_blueprints-2.1.0.dist-info/licenses/LICENSE
aa_blueprints-2.1.0.dist-info/WHEEL
aa_blueprints-2.1.0.dist-info/METADATA
aa_blueprints-2.1.0.dist-info/RECORD
