Metadata-Version: 2.4
Name: aa-blueprints
Version: 2.1.0
Summary: Blueprint Library plugin for Alliance Auth.
Author-email: Erik Kalkoken <kalkoken87@gmail.com>, Rebecca Murphy <rebecca@rcmurphy.me>
Requires-Python: >=3.10
Classifier: Environment :: Web Environment
Classifier: Framework :: Django
Classifier: Framework :: Django :: 4.2
Classifier: Intended Audience :: Developers
Classifier: License :: OSI Approved :: GNU General Public License v3 (GPLv3)
Classifier: Operating System :: OS Independent
Classifier: Programming Language :: Python
Classifier: Programming Language :: Python :: 3.10
Classifier: Programming Language :: Python :: 3.11
Classifier: Programming Language :: Python :: 3.12
Classifier: Programming Language :: Python :: 3.13
Classifier: Topic :: Internet :: WWW/HTTP
Classifier: Topic :: Internet :: WWW/HTTP :: Dynamic Content
License-File: LICENSE
Requires-Dist: allianceauth-app-utils>=2.0b1
Requires-Dist: allianceauth>=4.8,<5
Requires-Dist: dj-datatables-view
Requires-Dist: django-eveuniverse>=1.6
Project-URL: Homepage, https://gitlab.com/eclipse-expeditions/aa-blueprints
